beetrace/__init__.py
beetrace/__main__.py
beetrace/beetrace.py
beetrace-0.1.0.dist-info/LICENSE
beetrace-0.1.0.dist-info/METADATA
beetrace-0.1.0.dist-info/WHEEL
beetrace-0.1.0.dist-info/entry_points.txt
beetrace-0.1.0.dist-info/top_level.txt
beetrace-0.1.0.dist-info/RECORD
