Metadata-Version: 2.1
Name: beetrace
Version: 0.1.0
Summary: Trace your python process line by line with low overhead!
Home-page: https://github.com/furkanonder/beetrace/
Author: Furkan Onder
Author-email: furkanonder@protonmail.com
License: MIT
Project-URL: Issues, https://github.com/furkanonder/beetrace/issues/
Project-URL: Changelog, https://github.com/furkanonder/beetrace/CHANGELOG/
Keywords: tracer
Classifier: Development Status :: 2 - Pre-Alpha
Classifier: License :: OSI Approved :: MIT License
Classifier: Operating System :: POSIX :: Linux
Classifier: Programming Language :: Python
Classifier: Programming Language :: Python :: 3
Classifier: Programming Language :: Python :: 3 :: Only
Classifier: Programming Language :: Python :: 3.6
Classifier: Programming Language :: Python :: 3.7
Classifier: Programming Language :: Python :: 3.8
Classifier: Programming Language :: Python :: 3.9
Classifier: Programming Language :: Python :: 3.10
Classifier: Programming Language :: Python :: Implementation :: CPython
Classifier: Environment :: Console
Classifier: Topic :: Software Development :: Libraries :: Python Modules
Requires-Python: >=3.7
License-File: LICENSE
Requires-Dist: psutil (==5.9.4)
Requires-Dist: rich (==13.0.1)
